{
  "category": "", 
  "copyright_text": "", 
  "description": "", 
  "duration": 1800, 
  "language": "", 
  "quality_notes": "", 
  "recorded": "2015-05-30", 
  "slug": "", 
  "source_url": "https://www.youtube.com/watch?v=GV8_qL-akOI", 
  "speakers": [], 
  "state": 1, 
  "summary": "", 
  "tags": [
    "People & Blogs"
  ], 
  "thumbnail_url": "https://i.ytimg.com/vi/GV8_qL-akOI/maxresdefault.jpg", 
  "title": "Healing a shell shocked infrastructure by Michele Finelli", 
  "whiteboard": ""
}